mouse/__init__.py
mouse/__main__.py
mouse/_generic.py
mouse/_mouse_event.py
mouse/_mouse_tests.py
mouse/_nixcommon.py
mouse/_nixmouse.py
mouse/_winmouse.py
mouse-0.7.0.dist-info/DESCRIPTION.rst
mouse-0.7.0.dist-info/METADATA
mouse-0.7.0.dist-info/RECORD
mouse-0.7.0.dist-info/WHEEL
mouse-0.7.0.dist-info/metadata.json
mouse-0.7.0.dist-info/top_level.txt
