Metadata-Version: 1.1
Name: mouse
Version: 0.7.0
Summary: Hook and simulate global mouse events in pure Python
Home-page: https://github.com/boppreh/mouse
Author: BoppreH
Author-email: boppreh@gmail.com
License: MIT
Keywords: mouse listen hook simulate automate
Platform: UNKNOWN
Classifier: Development Status :: 4 - Beta
Classifier: License :: OSI Approved :: MIT License
Classifier: Operating System :: Microsoft :: Windows
Classifier: Operating System :: Unix
Classifier: Operating System :: MacOS :: MacOS X
Classifier: Programming Language :: Python :: 2
Classifier: Programming Language :: Python :: 3
Classifier: Topic :: Software Development :: Libraries :: Python Modules
Classifier: Topic :: Utilities
